kAuto/__init__.py
kAuto/create.py
kAuto/main.py
kAuto/source/__init__.py
kAuto/source/config.yml
kAuto/source/config_prod.yml
kAuto/source/main.py
kAuto/source/pytest.ini
kAuto/source/requirements.txt
kAuto/source/test.py
kAuto/source/api/__init__.py
kAuto/source/api/fronted_api.py
kAuto/source/api/group_api.py
kAuto/source/api/login_api.py
kAuto/source/api/parking_data_api.py
kAuto/source/api/parking_hk_api.py
kAuto/source/core/__init__.py
kAuto/source/core/base_request.py
kAuto/source/core/cloud_request.py
kAuto/source/core/group_request.py
kAuto/source/logs/__init__.py
kAuto/source/reports/__init__.py
kAuto/source/service/__init__.py
kAuto/source/service/bi_ana/__init__.py
kAuto/source/service/bi_ana/data_service.py
kAuto/source/service/bi_ana/parkAna_service.py
kAuto/source/service/bi_ana/parkReport_service.py
kAuto/source/service/bi_ana/statistic_service.py
kAuto/source/service/dashboard/__init__.py
kAuto/source/service/dashboard/dashboard_service.py
kAuto/source/service/login/__init__.py
kAuto/source/service/login/login_service.py
kAuto/source/service/plat_manager/__init__.py
kAuto/source/service/plat_manager/platManager_service.py
kAuto/source/service/report_center/__init__.py
kAuto/source/service/report_center/basic_report_service.py
kAuto/source/service/report_center/detail_report_service.py
kAuto/source/service/report_center/sta_report_service.py
kAuto/source/store/__init__.py
kAuto/source/store/store.py
kAuto/source/testCases/__init__.py
kAuto/source/testCases/conftest.py
kAuto/source/testCases/bi_ana/__init__.py
kAuto/source/testCases/bi_ana/test_data.py
kAuto/source/testCases/bi_ana/test_parkAna.py
kAuto/source/testCases/bi_ana/test_parkReport.py
kAuto/source/testCases/bi_ana/test_statistic.py
kAuto/source/testCases/dashboard/__init__.py
kAuto/source/testCases/dashboard/test_dashboard.py
kAuto/source/testCases/plat_manager/__init__.py
kAuto/source/testCases/plat_manager/test_platManager.py
kAuto/source/testCases/report_center/__init__.py
kAuto-1.0.dist-info/METADATA
kAuto-1.0.dist-info/WHEEL
kAuto-1.0.dist-info/entry_points.txt
kAuto-1.0.dist-info/top_level.txt
kAuto-1.0.dist-info/RECORD
