Metadata-Version: 2.1
Name: kAuto
Version: 1.0
Summary: keytop autotest framework
Home-page: https://www.keytop.com.cn
Author: yyyh
Author-email: huyuan@keytop.com
License: MIT
Platform: UNKNOWN
